upf_tools/__init__.py
upf_tools/__main__.py
upf_tools/api.py
upf_tools/cli.py
upf_tools/projectors.py
upf_tools/py.typed
upf_tools/upfdict.py
upf_tools/utils.py
upf_tools/v1.py
upf_tools/v2.py
upf_tools/version.py
upf_tools-0.1.9.dist-info/LICENSE
upf_tools-0.1.9.dist-info/METADATA
upf_tools-0.1.9.dist-info/WHEEL
upf_tools-0.1.9.dist-info/entry_points.txt
upf_tools-0.1.9.dist-info/top_level.txt
upf_tools-0.1.9.dist-info/RECORD
