Metadata-Version: 2.1
Name: upf-tools
Version: 0.1.9
Summary: Tools for handling .upf (Unified Pseudopotential Format) files
Home-page: https://github.com/pseudopotential-tools/upf-tools
Download-URL: https://github.com/pseudopotential-tools/upf-tools/releases
Author: Edward Linscott
Author-email: edwardlinscott@gmail.com
Maintainer: Edward Linscott
Maintainer-email: edwardlinscott@gmail.com
License: MIT
Project-URL: Bug Tracker, https://github.com/pseudopotential-tools/upf-tools/issues
Project-URL: Source Code, https://github.com/pseudopotential-tools/upf-tools
Keywords: snekpack,cookiecutter
Classifier: Development Status :: 1 - Planning
Classifier: Environment :: Console
Classifier: Intended Audience :: Developers
Classifier: License :: OSI Approved :: MIT License
Classifier: Operating System :: OS Independent
Classifier: Framework :: Pytest
Classifier: Framework :: tox
Classifier: Framework :: Sphinx
Classifier: Programming Language :: Python
Classifier: Programming Language :: Python :: 3.8
Classifier: Programming Language :: Python :: 3.9
Classifier: Programming Language :: Python :: 3.10
Classifier: Programming Language :: Python :: 3.11
Classifier: Programming Language :: Python :: 3 :: Only
Requires-Python: >=3.8
License-File: LICENSE
Requires-Dist: more-itertools
Requires-Dist: tqdm
Requires-Dist: click
Requires-Dist: more-click
Requires-Dist: numpy
Requires-Dist: packaging
Requires-Dist: typing
Requires-Dist: defusedxml
Requires-Dist: matplotlib
Requires-Dist: oncvpsp-tools
Provides-Extra: docs
Requires-Dist: sphinx <7.0 ; extra == 'docs'
Requires-Dist: sphinx-rtd-theme ; extra == 'docs'
Requires-Dist: sphinx-click ; extra == 'docs'
Requires-Dist: sphinx-autodoc-typehints ; extra == 'docs'
Requires-Dist: sphinx-automodapi ; extra == 'docs'
Provides-Extra: tests
Requires-Dist: pytest ; extra == 'tests'
Requires-Dist: coverage ; extra == 'tests'
